OptimalRegressor/ClassifyDatasets.py
OptimalRegressor/OptimalDTR.py
OptimalRegressor/OptimalGBR.py
OptimalRegressor/OptimalKNN.py
OptimalRegressor/OptimalLinear.py
OptimalRegressor/OptimalRF.py
OptimalRegressor/OptimalSVM.py
OptimalRegressor/OptimalXGB.py
OptimalRegressor/__init__.py
OptimalRegressor/regressors.py
optimal_regressors-1.0.0.dist-info/METADATA
optimal_regressors-1.0.0.dist-info/WHEEL
optimal_regressors-1.0.0.dist-info/top_level.txt
optimal_regressors-1.0.0.dist-info/RECORD
