Metadata-Version: 2.1
Name: optimal-regressors
Version: 1.0.0
Summary: A Python library to find optimal configurations for regressors and the overall best model.
Home-page: https://github.com/RehanTaneja/OptimalRegressors.git
Author: Rehan Taneja
Author-email: rehan.taneja4321@gmail.com
Classifier: Programming Language :: Python :: 3
Classifier: License :: OSI Approved :: MIT License
Classifier: Operating System :: OS Independent
Requires-Python: >=3.6
Requires-Dist: scikit-learn
Requires-Dist: xgboost
